haip/__init__.py
haip/confluence.py
haip_confluence-0.1.1.dist-info/LICENSE
haip_confluence-0.1.1.dist-info/METADATA
haip_confluence-0.1.1.dist-info/WHEEL
haip_confluence-0.1.1.dist-info/top_level.txt
haip_confluence-0.1.1.dist-info/RECORD
