Metadata-Version: 2.1
Name: haip-confluence
Version: 0.1.1
Summary: A Confluence API client.
Home-page: https://github.com/haipdev/confluence
Author: Reinhard Hainz
Author-email: reinhard.hainz@gmail.com
License: UNKNOWN
Platform: UNKNOWN
Classifier: Programming Language :: Python :: 3
Classifier: License :: OSI Approved :: MIT License
Classifier: Operating System :: OS Independent
Requires-Dist: aiohttp
Requires-Dist: haip-config
Requires-Dist: haip-template
